<timetable station="Frankfurt(Main)Hbf" eva="8000105">

<s id="6519626148103819066-2411041048-5" eva="8000105">
    <m id="r2309201" t="h" from="2411041256" to="2411042210" cat="Information" ts="2411041210" ts-tts="24-11-04 12:10:41.132" pr="2"/>
    <m id="r2309259" t="h" from="2411041357" to="2411041600" cat="Störung" ts="2411041400" ts-tts="24-11-04 14:00:18.361" pr="1"/>
    <m id="r296111970" t="c" ts="2411041355" ts-tts="24-11-04 13:55:52.171"/>
    <m id="r296111969" t="c" ts="2411041355" ts-tts="24-11-04 13:55:52.171"/>
    <m id="r296111966alt" t="c" ts="2411041355" ts-tts="24-11-04 13:55:52.340"/>
    <m id="r296111966" t="c" ts="2411041355" ts-tts="24-11-04 13:55:52.171"/>
    <m id="r296111967" t="c" ts="2411041355" ts-tts="24-11-04 13:55:52.171"/>
    <m id="r296111968" t="c" ts="2411041355" ts-tts="24-11-04 13:55:52.171"/>
    <ar ct="2411041419">
        <m id="r8993179" t="d" c="35" ts="2411040939" ts-tts="24-11-04 09:39:58.219"/>
        <m id="r8995143" t="q" c="80" ts="2411041018" ts-tts="24-11-04 10:18:25.961"/>
        <m id="r8995145" t="q" c="80" ts="2411041018" ts-tts="24-11-04 10:18:25.961"/>
        <m id="r8995147" t="q" c="80" ts="2411041018" ts-tts="24-11-04 10:18:25.961"/>
        <m id="r8996254" t="d" c="63" ts="2411041043" ts-tts="24-11-04 10:43:05.171"/>
        <m id="r8996273" t="q" c="80" ts="2411041043" ts-tts="24-11-04 10:43:36.368"/>
        <m id="r8996275" t="q" c="80" ts="2411041043" ts-tts="24-11-04 10:43:36.368"/>
        <m id="r8996277" t="q" c="80" ts="2411041043" ts-tts="24-11-04 10:43:36.368"/>
        <m id="r8996930" t="q" c="84" ts="2411041055" ts-tts="24-11-04 10:56:05.044"/>
        <m id="r8996932" t="q" c="80" ts="2411041055" ts-tts="24-11-04 10:56:05.044"/>
        <m id="r8996934" t="q" c="84" ts="2411041055" ts-tts="24-11-04 10:56:05.044"/>
        <m id="r8997118" t="q" c="80" ts="2411041101" ts-tts="24-11-04 11:01:32.227"/>
        <m id="r8997120" t="q" c="84" ts="2411041101" ts-tts="24-11-04 11:01:32.227"/>
        <m id="r8997122" t="q" c="84" ts="2411041101" ts-tts="24-11-04 11:01:32.227"/>
        <m id="r8999800" t="q" c="95" ts="2411041150" ts-tts="24-11-04 11:50:08.991"/>
        <m id="r9000402" t="q" c="80" ts="2411041201" ts-tts="24-11-04 12:01:49.144"/>
        <m id="r9000404" t="q" c="80" ts="2411041201" ts-tts="24-11-04 12:01:49.144"/>
        <m id="r9000918" t="q" c="80" ts="2411041215" ts-tts="24-11-04 12:15:37.112"/>
        <m id="r9000920" t="q" c="80" ts="2411041215" ts-tts="24-11-04 12:15:37.112"/>
        <m id="r9003703" t="d" c="43" ts="2411041313" ts-tts="24-11-04 13:13:08.508"/>
        <m id="r9005704" t="f" c="0" ts="2411041355" ts-tts="24-11-04 13:55:52.233"/>
        <m id="r9005890" t="d" c="64" ts="2411041359" ts-tts="24-11-04 13:59:46.536"/>
    </ar>
    <dp ct="2411041425">
        <m id="r8993179" t="d" c="35" ts="2411040939" ts-tts="24-11-04 09:39:58.219"/>
        <m id="r8995143" t="q" c="80" ts="2411041018" ts-tts="24-11-04 10:18:25.961"/>
        <m id="r8995145" t="q" c="80" ts="2411041018" ts-tts="24-11-04 10:18:25.961"/>
        <m id="r8995147" t="q" c="80" ts="2411041018" ts-tts="24-11-04 10:18:25.961"/>
        <m id="r8996254" t="d" c="63" ts="2411041043" ts-tts="24-11-04 10:43:05.171"/>
        <m id="r8996273" t="q" c="80" ts="2411041043" ts-tts="24-11-04 10:43:36.368"/>
        <m id="r8996275" t="q" c="80" ts="2411041043" ts-tts="24-11-04 10:43:36.368"/>
        <m id="r8996277" t="q" c="80" ts="2411041043" ts-tts="24-11-04 10:43:36.368"/>
        <m id="r8996930" t="q" c="84" ts="2411041055" ts-tts="24-11-04 10:56:05.044"/>
        <m id="r8996932" t="q" c="80" ts="2411041055" ts-tts="24-11-04 10:56:05.044"/>
        <m id="r8996934" t="q" c="84" ts="2411041055" ts-tts="24-11-04 10:56:05.044"/>
        <m id="r8997118" t="q" c="80" ts="2411041101" ts-tts="24-11-04 11:01:32.227"/>
        <m id="r8997120" t="q" c="84" ts="2411041101" ts-tts="24-11-04 11:01:32.227"/>
        <m id="r8997122" t="q" c="84" ts="2411041101" ts-tts="24-11-04 11:01:32.227"/>
        <m id="r8999800" t="q" c="95" ts="2411041150" ts-tts="24-11-04 11:50:08.991"/>
        <m id="r9000402" t="q" c="80" ts="2411041201" ts-tts="24-11-04 12:01:49.144"/>
        <m id="r9000404" t="q" c="80" ts="2411041201" ts-tts="24-11-04 12:01:49.144"/>
        <m id="r9000918" t="q" c="80" ts="2411041215" ts-tts="24-11-04 12:15:37.112"/>
        <m id="r9000920" t="q" c="80" ts="2411041215" ts-tts="24-11-04 12:15:37.112"/>
        <m id="r9003703" t="d" c="43" ts="2411041313" ts-tts="24-11-04 13:13:08.508"/>
        <m id="r9005890" t="d" c="64" ts="2411041359" ts-tts="24-11-04 13:59:46.536"/>
    </dp>
</s>


<s id="4037805516420832998-2411040727-14" eva="8000105">
    <m id="r2307396" t="h" from="2411011224" to="2411102359" cat="Störung" ts="2411011239" ts-tts="24-11-04 13:16:14.573" pr="1"/>
    <m id="r2304423" t="h" from="2410280806" to="2411162359" cat="Information" ts="2410280813" ts-tts="24-11-03 23:16:13.854" pr="2"/>
    <ar cpth="Hamburg-Altona|Hamburg Dammtor|Hamburg Hbf|Hamburg-Harburg|Bremen Hbf|Osnabrück Hbf|Münster(Westf)Hbf|Dortmund Hbf|Hagen Hbf|Wuppertal Hbf|Düsseldorf Hbf|Köln Hbf|Frankfurt(M) Flughafen Fernbf" ppth="Hamburg-Altona|Hamburg Dammtor|Hamburg Hbf|Hamburg-Harburg|Bremen Hbf|Osnabrück Hbf|Münster(Westf)Hbf|Dortmund Hbf|Hagen Hbf|Wuppertal Hbf|Solingen Hbf|Köln Hbf|Frankfurt(M) Flughafen Fernbf" cp="2" pp="1" ct="2411041432" pt="2411041303">
        <m id="r8984544" t="q" c="80" ts="2411040657" ts-tts="24-11-04 06:57:27.824"/>
        <m id="r8984546" t="q" c="80" ts="2411040657" ts-tts="24-11-04 06:57:27.824"/>
        <m id="r8985007" t="d" c="17" ts="2411040708" ts-tts="24-11-04 07:08:21.851"/>
        <m id="r8985041" t="q" c="80" ts="2411040708" ts-tts="24-11-04 07:08:37.444"/>
        <m id="r8985043" t="q" c="80" ts="2411040708" ts-tts="24-11-04 07:08:37.444"/>
        <m id="r8985127" t="d" c="47" ts="2411040709" ts-tts="24-11-04 07:10:10.976"/>
        <m id="r8987082" t="d" c="47" ts="2411040744" ts-tts="24-11-04 07:45:01.127"/>
        <m id="r8995135" t="d" c="64" ts="2411041018" ts-tts="24-11-04 10:18:25.961"/>
        <m id="r9000821" t="d" c="43" ts="2411041212" ts-tts="24-11-04 12:12:30.409"/>
        <m id="r9001956" t="f" c="0" ts="2411041234" ts-tts="24-11-04 12:34:38.438"/>
        <m id="r9002480" t="f" c="0" ts="2411041246" ts-tts="24-11-04 12:46:36.129"/>
        <m id="r9004272" t="f" c="0" ts="2411041323" ts-tts="24-11-04 13:23:33.841"/>
    </ar>
    <tl f="F" t="p" o="80" c="ICE" n="1907"/>
</s>


<s id="3704713885565394549-2411041036-11" eva="8000105">
    <ar ct="2411041427">
        <m id="r9004764" t="d" c="31" ts="2411041335" ts-tts="24-11-04 13:35:17.835"/>
    </ar>
    <dp ct="2411041433">
        <m id="r9004764" t="d" c="31" ts="2411041335" ts-tts="24-11-04 13:35:17.835"/>
        <m id="r9005006" t="f" c="0" ts="2411041340" ts-tts="24-11-04 13:41:01.691"/>
        <m id="r9005010" t="f" c="0" ts="2411041340" ts-tts="24-11-04 13:41:01.691"/>
    </dp>
</s>


<s id="-8122478520125021856-2411041319-13" eva="8000105">
    <ar ct="2411041433" l="22"/>
</s>


<s id="8780351192518057290-2411040928-15" eva="8000105">
    <m id="r2304423" t="h" from="2410280806" to="2411162359" cat="Information" ts="2410280813" ts-tts="24-11-03 23:16:13.854" pr="2"/>
    <ar ppth="Hamburg-Altona|Hamburg Dammtor|Hamburg Hbf|Hamburg-Harburg|Bremen Hbf|Osnabrück Hbf|Münster(Westf)Hbf|Dortmund Hbf|Bochum Hbf|Essen Hbf|Duisburg Hbf|Düsseldorf Hbf|Köln Hbf|Frankfurt(M) Flughafen Fernbf" pp="1" ct="2411041538" pt="2411041503">
        <m id="r8990250" t="f" c="0" ts="2411040840" ts-tts="24-11-04 08:40:27.094"/>
        <m id="r9004354" t="d" c="43" ts="2411041325" ts-tts="24-11-04 13:25:22.927"/>
        <m id="r9006205" t="d" c="17" ts="2411041402" ts-tts="24-11-04 14:02:23.782"/>
    </ar>
    <tl f="F" t="p" o="80" c="ICE" n="1909"/>
</s>


<s id="3548469924766987265-2411041223-12" eva="8000105">
    <ar ct="2411041442" l="30"/>
</s>


<s id="-2197447328720659546-2411041137-28" eva="8000105">
    <ar ct="2411041404" l="RB10"/>
</s>


<s id="-3238798974880651162-2411041231-10" eva="8000105">
    <ar ppth="Nidderau|Nidderau-Windecken|Schöneck-Büdesheim|Schöneck-Kilianstädten|Schöneck-Oberdorfelden|Niederdorfelden|Bad Vilbel-Gronau|Bad Vilbel|Frankfurt(Main)West" pp="14" ct="2411041425" pt="2411041315" l="34">
        <m id="r9003441" t="d" c="8" ts="2411041306" ts-tts="24-11-04 13:06:53.261"/>
    </ar>
    <tl f="N" t="e" o="8005ND" c="RB" n="98766"/>
    <ref>
        <tl f="N" t="p" o="8005ND" c="RB" n="15725"/>
    </ref>
</s>


<s id="-2237137775459262366-2411041332-10" eva="8000105">
    <ar ct="2411041413" l="RB12"/>
</s>

</timetable>
