<timetable station="Frankfurt(Main)Hbf" eva="8000105">

<s id="-8586433411732575948-2411040841-1" eva="8000105">
    <dp ct="2411040841" l="34"/>
</s>


<s id="-5890722975720098232-2411040643-16" eva="8000105">
    <ar ct="2411040826" l="RB15"/>
</s>


<s id="4037805516420832998-2411040727-14" eva="8000105">
    <m id="r2307396" t="h" from="2411011224" to="2411041200" cat="Störung" ts="2411011239" ts-tts="24-11-03 23:16:14.627" pr="1"/>
    <m id="r2304423" t="h" from="2410280806" to="2411162359" cat="Information" ts="2410280813" ts-tts="24-11-03 23:16:14.559" pr="2"/>
    <ar cpth="Hamburg-Altona|Hamburg Dammtor|Hamburg Hbf|Hamburg-Harburg|Bremen Hbf|Osnabrück Hbf|Münster(Westf)Hbf|Dortmund Hbf|Hagen Hbf|Wuppertal Hbf|Düsseldorf Hbf|Köln Hbf|Frankfurt(M) Flughafen Fernbf" ct="2411041329">
        <m id="r8984544" t="q" c="80" ts="2411040657" ts-tts="24-11-04 06:57:25.556"/>
        <m id="r8984546" t="q" c="80" ts="2411040657" ts-tts="24-11-04 06:57:25.556"/>
        <m id="r8985007" t="d" c="17" ts="2411040708" ts-tts="24-11-04 07:08:21.595"/>
        <m id="r8985041" t="q" c="80" ts="2411040708" ts-tts="24-11-04 07:08:37.189"/>
        <m id="r8985043" t="q" c="80" ts="2411040708" ts-tts="24-11-04 07:08:37.189"/>
        <m id="r8985127" t="d" c="47" ts="2411040709" ts-tts="24-11-04 07:10:10.949"/>
        <m id="r8987082" t="d" c="47" ts="2411040744" ts-tts="24-11-04 07:45:03.574"/>
    </ar>
</s>


<s id="2801826025756613862-2411040817-1" eva="8000105">
    <dp ct="2411040824" l="RB12"/>
</s>


<s id="-6223962037244896084-2411040448-6" eva="8000105">
    <m id="r296109743alt" t="c" ts="2411040757" ts-tts="24-11-04 07:57:34.821"/>
    <m id="r296109799alt" t="c" ts="2411040809" ts-tts="24-11-04 08:10:04.245"/>
    <m id="r296109797alt" t="c" ts="2411040809" ts-tts="24-11-04 08:10:04.245"/>
    <m id="r296109798alt" t="c" ts="2411040809" ts-tts="24-11-04 08:10:04.245"/>
    <m id="r296109745alt" t="c" ts="2411040757" ts-tts="24-11-04 07:57:34.821"/>
    <m id="r296109744alt" t="c" ts="2411040757" ts-tts="24-11-04 07:57:34.821"/>
    <m id="r296109746alt" t="c" ts="2411040757" ts-tts="24-11-04 07:57:34.821"/>
    <m id="r296109747alt" t="c" ts="2411040757" ts-tts="24-11-04 07:57:34.821"/>
    <m id="r296109744" t="c" ts="2411040757" ts-tts="24-11-04 07:57:34.618"/>
    <m id="r296109801alt" t="c" ts="2411040809" ts-tts="24-11-04 08:10:04.245"/>
    <m id="r296109745" t="c" ts="2411040757" ts-tts="24-11-04 07:57:34.618"/>
    <m id="r296109802alt" t="c" ts="2411040809" ts-tts="24-11-04 08:10:04.245"/>
    <m id="r296109800alt" t="c" ts="2411040809" ts-tts="24-11-04 08:10:04.245"/>
    <m id="r296109743" t="c" ts="2411040757" ts-tts="24-11-04 07:57:34.618"/>
    <m id="r296109746" t="c" ts="2411040757" ts-tts="24-11-04 07:57:34.618"/>
    <m id="r296109747" t="c" ts="2411040757" ts-tts="24-11-04 07:57:34.618"/>
    <ar ct="2411040812">
        <m id="r8987518" t="d" c="43" ts="2411040754" ts-tts="24-11-04 07:54:26.498"/>
        <m id="r8987865" t="f" c="0" ts="2411040757" ts-tts="24-11-04 07:57:34.699"/>
        <m id="r8987869" t="f" c="0" ts="2411040757" ts-tts="24-11-04 07:57:34.699"/>
        <m id="r8987875" t="f" c="0" ts="2411040757" ts-tts="24-11-04 07:57:34.699"/>
        <m id="r8987879" t="f" c="0" ts="2411040757" ts-tts="24-11-04 07:57:34.699"/>
        <m id="r8987884" t="f" c="0" ts="2411040757" ts-tts="24-11-04 07:57:34.699"/>
    </ar>
    <dp ct="2411040818">
        <m id="r8987518" t="d" c="43" ts="2411040754" ts-tts="24-11-04 07:54:26.498"/>
    </dp>
</s>


<s id="-2207613486972401003-2411040652-12" eva="8000105">
    <ar ct="2411040842" l="2">
        <m id="r8988076" t="f" c="0" ts="2411040800" ts-tts="24-11-04 08:00:10.651"/>
    </ar>
</s>


<s id="-2115090395893225760-2411040813-12" eva="8000105">
    <ar ct="2411040902" l="61">
        <m id="r8970131" t="f" c="0" ts="2411031843" ts-tts="24-11-03 18:43:38.840"/>
        <m id="r8970132" t="f" c="1000" ts="2411031843" ts-tts="24-11-03 18:43:38.840"/>
        <m id="r8970133" t="q" c="85" ts="2411031843" ts-tts="24-11-03 18:43:38.840"/>
    </ar>
</s>


<s id="5394868531176279031-2411040747-6" eva="8000105">
    <ar ct="2411041111">
        <m id="r8983298" t="d" c="47" ts="2411040629" ts-tts="24-11-04 06:29:54.681"/>
        <m id="r8985527" t="q" c="80" ts="2411040717" ts-tts="24-11-04 07:17:28.053"/>
        <m id="r8985529" t="q" c="80" ts="2411040717" ts-tts="24-11-04 07:17:28.053"/>
    </ar>
    <dp ct="2411041117">
        <m id="r8983298" t="d" c="47" ts="2411040629" ts-tts="24-11-04 06:29:54.681"/>
        <m id="r8985527" t="q" c="80" ts="2411040717" ts-tts="24-11-04 07:17:28.053"/>
        <m id="r8985529" t="q" c="80" ts="2411040717" ts-tts="24-11-04 07:17:28.053"/>
    </dp>
</s>


<s id="-943782869423150951-2411040712-14" eva="8000105">
    <ar ct="2411040815" l="51"/>
</s>


<s id="-223354783277510420-2411040802-1" eva="8000105">
    <dp ct="2411040810">
        <m id="r8987430" t="f" c="0" ts="2411040752" ts-tts="24-11-04 07:52:21.847"/>
        <m id="r8987432" t="f" c="0" ts="2411040752" ts-tts="24-11-04 07:52:21.847"/>
        <m id="r8988057" t="q" c="80" ts="2411040759" ts-tts="24-11-04 07:59:55.079"/>
        <m id="r8988545" t="f" c="0" ts="2411040809" ts-tts="24-11-04 08:09:32.869"/>
    </dp>
</s>


<s id="896384667678103556-2411040732-10" eva="8000105">
    <ar ct="2411040823" l="RB12"/>
</s>


<s id="4310096410363676106-2411040732-16" eva="8000105">
    <ar ct="2411040900" l="34">
        <m id="r8974351" t="f" c="0" ts="2411032035" ts-tts="24-11-03 20:35:37.614"/>
        <m id="r8974352" t="f" c="1000" ts="2411032035" ts-tts="24-11-03 20:35:37.614"/>
        <m id="r8974353" t="q" c="85" ts="2411032035" ts-tts="24-11-03 20:35:37.614"/>
        <m id="r8985158" t="d" c="47" ts="2411040710" ts-tts="24-11-04 07:10:57.656"/>
    </ar>
</s>


<s id="-8338217849521596952-2411040636-10" eva="8000105">
    <m id="r2307396" t="h" from="2411011224" to="2411041200" cat="Störung" ts="2411011239" ts-tts="24-11-03 23:16:14.627" pr="1"/>
    <ar cpth="Dortmund Hbf|Hagen Hbf|Wuppertal Hbf|Düsseldorf Hbf|Köln Hbf|Bonn Hbf|Koblenz Hbf|Mainz Hbf|Frankfurt(M) Flughafen Fernbf" ppth="Dortmund Hbf|Hagen Hbf|Wuppertal Hbf|Solingen Hbf|Köln Hbf|Bonn Hbf|Koblenz Hbf|Mainz Hbf|Frankfurt(M) Flughafen Fernbf" pp="5" ct="2411041128" pt="2411041013">
        <m id="r8971161" t="q" c="90" ts="2411031906" ts-tts="24-11-03 19:06:40.736"/>
        <m id="r8979287" t="f" c="0" ts="2411040133" ts-tts="24-11-04 01:33:19.014"/>
        <m id="r8982330" t="q" c="84" ts="2411040606" ts-tts="24-11-04 06:06:20.574"/>
        <m id="r8982332" t="q" c="80" ts="2411040606" ts-tts="24-11-04 06:06:20.574"/>
        <m id="r8982334" t="q" c="84" ts="2411040606" ts-tts="24-11-04 06:06:20.574"/>
        <m id="r8983931" t="d" c="31" ts="2411040642" ts-tts="24-11-04 06:42:52.995"/>
        <m id="r8983941" t="d" c="40" ts="2411040643" ts-tts="24-11-04 06:43:24.061"/>
        <m id="r8984728" t="d" c="17" ts="2411040701" ts-tts="24-11-04 07:01:20.370"/>
        <m id="r8984742" t="q" c="80" ts="2411040701" ts-tts="24-11-04 07:01:51.514"/>
        <m id="r8984744" t="q" c="80" ts="2411040701" ts-tts="24-11-04 07:01:51.514"/>
        <m id="r8984755" t="f" c="0" ts="2411040701" ts-tts="24-11-04 07:01:51.515"/>
        <m id="r8985396" t="f" c="0" ts="2411040715" ts-tts="24-11-04 07:15:23.175"/>
        <m id="r8985929" t="f" c="0" ts="2411040724" ts-tts="24-11-04 07:25:01.322"/>
    </ar>
    <dp cpth="Hanau Hbf|Würzburg Hbf|Nürnberg Hbf|Ingolstadt Hbf|München Hbf" ppth="Hanau Hbf|Würzburg Hbf|Nürnberg Hbf|Ingolstadt Hbf|München Hbf" pp="5" ct="2411041134" pt="2411041022">
        <m id="r8971161" t="q" c="90" ts="2411031906" ts-tts="24-11-03 19:06:40.736"/>
        <m id="r8979287" t="f" c="0" ts="2411040133" ts-tts="24-11-04 01:33:19.014"/>
        <m id="r8982330" t="q" c="84" ts="2411040606" ts-tts="24-11-04 06:06:20.574"/>
        <m id="r8982332" t="q" c="80" ts="2411040606" ts-tts="24-11-04 06:06:20.574"/>
        <m id="r8982334" t="q" c="84" ts="2411040606" ts-tts="24-11-04 06:06:20.574"/>
        <m id="r8983931" t="d" c="31" ts="2411040642" ts-tts="24-11-04 06:42:52.995"/>
        <m id="r8983941" t="d" c="40" ts="2411040643" ts-tts="24-11-04 06:43:24.061"/>
        <m id="r8984728" t="d" c="17" ts="2411040701" ts-tts="24-11-04 07:01:20.370"/>
        <m id="r8984742" t="q" c="80" ts="2411040701" ts-tts="24-11-04 07:01:51.515"/>
        <m id="r8984744" t="q" c="80" ts="2411040701" ts-tts="24-11-04 07:01:51.515"/>
        <m id="r8984755" t="f" c="0" ts="2411040701" ts-tts="24-11-04 07:01:51.515"/>
        <m id="r8985396" t="f" c="0" ts="2411040715" ts-tts="24-11-04 07:15:23.175"/>
        <m id="r8985929" t="f" c="0" ts="2411040724" ts-tts="24-11-04 07:25:01.322"/>
    </dp>
    <tl f="F" t="p" o="80" c="ICE" n="1621"/>
</s>


<s id="6063089077175050611-2411040818-1" eva="8000105">
    <dp ct="2411040820" l="5">
        <m id="r8988600" t="f" c="0" ts="2411040809" ts-tts="24-11-04 08:10:04.099"/>
        <m id="r8988602" t="f" c="0" ts="2411040809" ts-tts="24-11-04 08:10:04.099"/>
    </dp>
</s>


<s id="-8649114451878612041-2411040720-15" eva="8000105">
    <ar ct="2411040845" l="RB61">
        <m id="r8988046" t="d" c="44" ts="2411040759" ts-tts="24-11-04 07:59:39.450"/>
    </ar>
</s>


<s id="-853844594697067860-2411040622-8" eva="8000105">
    <m id="r2308997" t="h" from="2411040430" to="2411040630" cat="Störung" ts="2411040528" ts-tts="24-11-04 05:28:38.220" pr="1"/>
    <ar ct="2411040848">
        <m id="r8944435" t="f" c="0" ts="2411030024" ts-tts="24-11-03 00:24:33.074"/>
        <m id="r8945725" t="f" c="0" ts="2411030145" ts-tts="24-11-03 01:46:01.805"/>
    </ar>
    <dp ct="2411040855">
        <m id="r8944435" t="f" c="0" ts="2411030024" ts-tts="24-11-03 00:24:33.074"/>
        <m id="r8945725" t="f" c="0" ts="2411030145" ts-tts="24-11-03 01:46:01.805"/>
        <m id="r8988599" t="f" c="0" ts="2411040809" ts-tts="24-11-04 08:10:04.099"/>
    </dp>
</s>


<s id="-8462479539414286916-2411040614-23" eva="8000105">
    <ar ct="2411040813" l="RB41"/>
</s>


<s id="-4672624831052266237-2411040631-19" eva="8000105">
    <ar ct="2411040813" l="RB40"/>
</s>


<s id="5509309536167095600-2411040553-5" eva="8000105">
    <ar ct="2411040904">
        <m id="r8981177" t="q" c="80" ts="2411040523" ts-tts="24-11-04 05:23:28.454"/>
        <m id="r8981179" t="q" c="80" ts="2411040523" ts-tts="24-11-04 05:23:28.454"/>
        <m id="r8981181" t="q" c="80" ts="2411040523" ts-tts="24-11-04 05:23:28.454"/>
    </ar>
    <dp ct="2411040911">
        <m id="r8981177" t="q" c="80" ts="2411040523" ts-tts="24-11-04 05:23:28.454"/>
        <m id="r8981179" t="q" c="80" ts="2411040523" ts-tts="24-11-04 05:23:28.454"/>
        <m id="r8981181" t="q" c="80" ts="2411040523" ts-tts="24-11-04 05:23:28.454"/>
        <m id="r8987867" t="f" c="0" ts="2411040757" ts-tts="24-11-04 07:57:34.699"/>
        <m id="r8987871" t="f" c="0" ts="2411040757" ts-tts="24-11-04 07:57:34.699"/>
        <m id="r8988586" t="f" c="0" ts="2411040809" ts-tts="24-11-04 08:10:04.099"/>
        <m id="r8988592" t="f" c="0" ts="2411040809" ts-tts="24-11-04 08:10:04.099"/>
    </dp>
</s>


<s id="-8368238155127969333-2411040854-1" eva="8000105">
    <m id="r2307396" t="h" from="2411011224" to="2411041200" cat="Störung" ts="2411011239" ts-tts="24-11-03 23:16:14.627" pr="1"/>
    <m id="r2304423" t="h" from="2410280806" to="2411162359" cat="Information" ts="2410280813" ts-tts="24-11-03 23:16:14.559" pr="2"/>
    <dp cpth="Frankfurt(M) Flughafen Fernbf|Köln Hbf|Düsseldorf Hbf|Wuppertal Hbf|Hagen Hbf|Dortmund Hbf|Münster(Westf)Hbf|Osnabrück Hbf|Bremen Hbf|Hamburg-Harburg|Hamburg Hbf|Hamburg Dammtor|Hamburg-Altona" ct="2411040854">
        <m id="r8970937" t="f" c="1000" ts="2411031900" ts-tts="24-11-03 19:00:43.440"/>
        <m id="r8985679" t="d" c="17" ts="2411040719" ts-tts="24-11-04 07:19:33.591"/>
        <m id="r8988585" t="f" c="0" ts="2411040809" ts-tts="24-11-04 08:10:04.099"/>
        <m id="r8988591" t="f" c="0" ts="2411040809" ts-tts="24-11-04 08:10:04.099"/>
    </dp>
</s>


<s id="4517498801247346569-2411040826-1" eva="8000105">
    <dp ct="2411040826" l="50">
        <m id="r8988603" t="f" c="0" ts="2411040809" ts-tts="24-11-04 08:10:04.099"/>
    </dp>
</s>


<s id="-5717720788505540143-2411040816-1" eva="8000105">
    <dp ct="2411040816">
        <m id="r8987868" t="f" c="0" ts="2411040757" ts-tts="24-11-04 07:57:34.699"/>
        <m id="r8987870" t="f" c="0" ts="2411040757" ts-tts="24-11-04 07:57:34.699"/>
        <m id="r8988588" t="f" c="0" ts="2411040809" ts-tts="24-11-04 08:10:04.099"/>
        <m id="r8988590" t="f" c="0" ts="2411040809" ts-tts="24-11-04 08:10:04.099"/>
    </dp>
</s>


<s id="-3742581979109449988-2411040816-1" eva="8000105">
    <dp ct="2411040816">
        <m id="r8987864" t="f" c="0" ts="2411040757" ts-tts="24-11-04 07:57:34.699"/>
        <m id="r8987866" t="f" c="0" ts="2411040757" ts-tts="24-11-04 07:57:34.699"/>
        <m id="r8988582" t="f" c="0" ts="2411040809" ts-tts="24-11-04 08:10:04.099"/>
        <m id="r8988584" t="f" c="0" ts="2411040809" ts-tts="24-11-04 08:10:04.099"/>
    </dp>
</s>


<s id="-677385996155243799-2411040815-1" eva="8000105">
    <m id="r2308916" t="h" from="2411040009" to="2411041229" cat="Information" ts="2411040020" ts-tts="24-11-04 01:16:15.134" pr="2"/>
    <m id="r2276258" t="h" from="2409111443" to="2411112359" cat="Information" ts="2409120821" ts-tts="24-11-03 23:16:14.381" pr="2"/>
    <m id="r2308834" t="h" from="2411031724" to="2411072359" cat="Information" ts="2411031725" ts-tts="24-11-03 23:16:14.638" pr="3"/>
    <dp ct="2411040815">
        <m id="r8987092" t="q" c="80" ts="2411040745" ts-tts="24-11-04 07:45:19.246"/>
        <m id="r8987882" t="f" c="0" ts="2411040757" ts-tts="24-11-04 07:57:34.699"/>
        <m id="r8987885" t="f" c="0" ts="2411040757" ts-tts="24-11-04 07:57:34.699"/>
        <m id="r8988604" t="f" c="0" ts="2411040809" ts-tts="24-11-04 08:10:04.099"/>
    </dp>
</s>


<s id="3596733780499351643-2411040434-11" eva="8000105">
    <m id="r2309030" t="h" from="2411040802" to="2411042121" cat="Information" ts="2411040644" ts-tts="24-11-04 06:44:10.681" pr="2"/>
    <m id="r2308997" t="h" from="2411040430" to="2411040630" cat="Störung" ts="2411040528" ts-tts="24-11-04 05:28:38.220" pr="1"/>
    <ar cpth="" cp="5" ct="2411040813" cs="c" clt="2411040526">
        <m id="r8980318" t="q" c="80" ts="2411040404" ts-tts="24-11-04 04:04:23.667"/>
        <m id="r8980322" t="q" c="80" ts="2411040404" ts-tts="24-11-04 04:04:23.667"/>
        <m id="r8980568" t="d" c="31" ts="2411040441" ts-tts="24-11-04 04:41:46.157"/>
        <m id="r8980697" t="f" c="0" ts="2411040455" ts-tts="24-11-04 04:55:53.167"/>
        <m id="r8981233" t="f" c="0" ts="2411040525" ts-tts="24-11-04 05:26:03.042"/>
        <m id="r8981250" t="d" c="31" ts="2411040526" ts-tts="24-11-04 05:26:34.248"/>
        <m id="r8983509" t="f" c="0" ts="2411040633" ts-tts="24-11-04 06:33:32.075"/>
    </ar>
    <dp cpth="Hanau Hbf|Würzburg Hbf|Nürnberg Hbf|Regensburg Hbf|Plattling|Passau Hbf|Linz Hbf" cp="5" ct="2411040821">
        <m id="r8980318" t="q" c="80" ts="2411040404" ts-tts="24-11-04 04:04:23.667"/>
        <m id="r8980322" t="q" c="80" ts="2411040404" ts-tts="24-11-04 04:04:23.667"/>
        <m id="r8980568" t="d" c="31" ts="2411040441" ts-tts="24-11-04 04:41:46.157"/>
        <m id="r8980697" t="f" c="0" ts="2411040455" ts-tts="24-11-04 04:55:53.167"/>
        <m id="r8981233" t="f" c="0" ts="2411040525" ts-tts="24-11-04 05:26:03.042"/>
        <m id="r8981250" t="d" c="31" ts="2411040526" ts-tts="24-11-04 05:26:34.248"/>
        <m id="r8983509" t="f" c="0" ts="2411040633" ts-tts="24-11-04 06:33:32.075"/>
        <m id="r8988596" t="f" c="0" ts="2411040809" ts-tts="24-11-04 08:10:04.099"/>
        <m id="r8988598" t="f" c="0" ts="2411040809" ts-tts="24-11-04 08:10:04.099"/>
    </dp>
</s>


<s id="-6004557489205239816-2411040508-6" eva="8000105">
    <m id="r2305119" t="h" from="2411040542" to="2411040631" cat="Bauarbeiten" ts="2411032302" ts-tts="24-11-03 23:02:52.694" pr="1"/>
    <m id="r2308955" t="h" from="2411040416" to="2411050052" cat="Information" ts="2411040235" ts-tts="24-11-04 02:35:29.920" pr="3"/>
    <m id="r296109805" t="c" ts="2411040809" ts-tts="24-11-04 08:10:04.034"/>
    <m id="r296109799alt" t="c" ts="2411040809" ts-tts="24-11-04 08:10:04.245"/>
    <m id="r296109797alt" t="c" ts="2411040809" ts-tts="24-11-04 08:10:04.245"/>
    <m id="r296109798alt" t="c" ts="2411040809" ts-tts="24-11-04 08:10:04.245"/>
    <m id="r296109799" t="c" ts="2411040809" ts-tts="24-11-04 08:10:04.034"/>
    <m id="r296109801alt" t="c" ts="2411040809" ts-tts="24-11-04 08:10:04.245"/>
    <m id="r296109800" t="c" ts="2411040809" ts-tts="24-11-04 08:10:04.034"/>
    <m id="r296109802alt" t="c" ts="2411040809" ts-tts="24-11-04 08:10:04.245"/>
    <m id="r296109797" t="c" ts="2411040809" ts-tts="24-11-04 08:10:04.034"/>
    <m id="r296109800alt" t="c" ts="2411040809" ts-tts="24-11-04 08:10:04.245"/>
    <m id="r296109798" t="c" ts="2411040809" ts-tts="24-11-04 08:10:04.034"/>
    <m id="r296109803" t="c" ts="2411040809" ts-tts="24-11-04 08:10:04.034"/>
    <m id="r296109804alt" t="c" ts="2411040809" ts-tts="24-11-04 08:10:04.245"/>
    <m id="r296109804" t="c" ts="2411040809" ts-tts="24-11-04 08:10:04.034"/>
    <m id="r296109803alt" t="c" ts="2411040809" ts-tts="24-11-04 08:10:04.245"/>
    <m id="r296109801" t="c" ts="2411040809" ts-tts="24-11-04 08:10:04.034"/>
    <m id="r296109802" t="c" ts="2411040809" ts-tts="24-11-04 08:10:04.034"/>
    <ar cpth="Basel Bad Bf|Freiburg(Breisgau) Hbf|Offenburg|Baden-Baden|Karlsruhe Hbf|Darmstadt Hbf" ct="2411040817">
        <m id="r8979771" t="q" c="85" ts="2411040212" ts-tts="24-11-04 02:12:31.643"/>
        <m id="r8980912" t="f" c="0" ts="2411040510" ts-tts="24-11-04 05:10:19.672"/>
        <m id="r8982793" t="d" c="43" ts="2411040617" ts-tts="24-11-04 06:17:59.736"/>
        <m id="r8988583" t="f" c="0" ts="2411040809" ts-tts="24-11-04 08:10:04.098"/>
        <m id="r8988589" t="f" c="0" ts="2411040809" ts-tts="24-11-04 08:10:04.098"/>
        <m id="r8988597" t="f" c="0" ts="2411040809" ts-tts="24-11-04 08:10:04.098"/>
        <m id="r8988601" t="f" c="0" ts="2411040809" ts-tts="24-11-04 08:10:04.099"/>
    </ar>
    <dp cpth="Fulda|Eisenach|Erfurt Hbf|Leipzig Hbf|Lutherstadt Wittenberg Hbf|Berlin Südkreuz|Berlin Hbf" ct="2411040823">
        <m id="r8979771" t="q" c="85" ts="2411040212" ts-tts="24-11-04 02:12:31.643"/>
        <m id="r8980912" t="f" c="0" ts="2411040510" ts-tts="24-11-04 05:10:19.672"/>
        <m id="r8982793" t="d" c="43" ts="2411040617" ts-tts="24-11-04 06:17:59.736"/>
        <m id="r8986121" t="f" c="0" ts="2411040729" ts-tts="24-11-04 07:29:10.815"/>
        <m id="r8987433" t="f" c="0" ts="2411040752" ts-tts="24-11-04 07:52:21.847"/>
    </dp>
</s>


<s id="-4676367904559688889-2411040847-5" eva="8000105">
    <ar ct="2411041204">
        <m id="r8986671" t="f" c="0" ts="2411040738" ts-tts="24-11-04 07:38:17.288"/>
    </ar>
    <dp ct="2411041211">
        <m id="r8986671" t="f" c="0" ts="2411040738" ts-tts="24-11-04 07:38:17.288"/>
    </dp>
</s>

</timetable>
