<timetable station="Frankfurt(Main)Hbf" eva="8000105">

<s id="2874625510607608743-2411020521-1" eva="8000105">
    <dp ct="2411020521" l="30">
        <m id="r8912878" t="f" c="0" ts="2411020059" ts-tts="24-11-02 00:59:33.715"/>
        <m id="r8912879" t="f" c="1000" ts="2411020059" ts-tts="24-11-02 00:59:33.715"/>
        <m id="r8912880" t="q" c="85" ts="2411020059" ts-tts="24-11-02 00:59:33.715"/>
    </dp>
</s>


<s id="1603709807881300763-2411020851-19" eva="8000105">
    <ar ct="2411021148" l="3"/>
</s>


<s id="-5453835309889600672-2411020450-1" eva="8000105">
    <dp ct="2411020451" l="RB58"/>
</s>


<s id="5604986967308545941-2411020519-13" eva="8000105">
    <ar ct="2411020648" l="2"/>
</s>

</timetable>
