<timetable station="Frankfurt(Main)Hbf" eva="8000105">

<s id="3080474508177482894-2410301851-9" eva="8000105">
    <m id="r2285183" t="h" from="2410010000" to="2411152359" cat="Information" ts="2409302303" ts-tts="24-10-29 23:16:13.886" pr="2"/>
    <ar ct="2410302352">
        <m id="r8815041" t="q" c="80" ts="2410301821" ts-tts="24-10-30 18:21:23.468"/>
        <m id="r8819536" t="d" c="24" ts="2410301939" ts-tts="24-10-30 19:39:58.628"/>
        <m id="r8819812" t="d" c="13" ts="2410301947" ts-tts="24-10-30 19:47:26.879"/>
        <m id="r8820678" t="f" c="0" ts="2410302011" ts-tts="24-10-30 20:11:22.978"/>
    </ar>
</s>


<s id="-7929720578321154182-2410301729-15" eva="8000105">
    <m id="r2304423" t="h" from="2410280806" to="2411102359" cat="Information" ts="2410280813" ts-tts="24-10-29 23:16:14.147" pr="2"/>
    <ar ct="2410310028"/>
</s>


<s id="1182223268081247614-2410301702-13" eva="8000105">
    <m id="r2306130" t="h" from="2410301702" to="2410302035" cat="Information" ts="2410301722" ts-tts="24-10-30 17:22:11.536" pr="2"/>
    <ar cpth="Dortmund Hbf|Witten Hbf|Letmathe|Altena(Westf)|Werdohl|Plettenberg|Finnentrop|Lennestadt-Grevenbrück|Lennestadt-Altenhundem|Kreuztal|Siegen-Weidenau|Siegen Hbf|Dillenburg|Wetzlar|Bad Nauheim|Frankfurt(Main)West" ppth="Dortmund Hbf|Witten Hbf|Letmathe|Altena(Westf)|Werdohl|Plettenberg|Finnentrop|Lennestadt-Grevenbrück|Lennestadt-Altenhundem|Kreuztal|Siegen-Weidenau|Siegen Hbf" pp="16" ct="2410302047" pt="2410302035">
        <m id="r8807554" t="f" c="0" ts="2410301600" ts-tts="24-10-30 16:00:39.702"/>
        <m id="r8807573" t="f" c="0" ts="2410301601" ts-tts="24-10-30 16:01:11.898"/>
        <m id="r8807594" t="f" c="0" ts="2410301601" ts-tts="24-10-30 16:02:00.069"/>
        <m id="r8807639" t="f" c="0" ts="2410301602" ts-tts="24-10-30 16:02:16.042"/>
        <m id="r8808344" t="d" c="36" ts="2410301615" ts-tts="24-10-30 16:15:09.469"/>
        <m id="r8814057" t="d" c="36" ts="2410301801" ts-tts="24-10-30 18:01:22.678"/>
        <m id="r8816626" t="f" c="0" ts="2410301851" ts-tts="24-10-30 18:51:17.055"/>
        <m id="r8816639" t="f" c="0" ts="2410301851" ts-tts="24-10-30 18:51:49.021"/>
        <m id="r8816648" t="f" c="0" ts="2410301851" ts-tts="24-10-30 18:52:05.082"/>
    </ar>
    <tl f="F" t="s" o="80" c="IC" n="2935"/>
</s>


<s id="-8312398823745694210-2410301511-8" eva="8000105">
    <m id="r2305520" t="h" from="2410300600" to="2410302359" cat="Information" ts="2410300336" ts-tts="24-10-30 03:36:40.307" pr="2"/>
    <ar ct="2410302020">
        <m id="r8803875" t="q" c="80" ts="2410301441" ts-tts="24-10-30 14:41:29.429"/>
        <m id="r8803877" t="q" c="80" ts="2410301441" ts-tts="24-10-30 14:41:29.429"/>
        <m id="r8811546" t="f" c="0" ts="2410301719" ts-tts="24-10-30 17:19:11.884"/>
        <m id="r8812304" t="f" c="0" ts="2410301730" ts-tts="24-10-30 17:30:18.463"/>
        <m id="r8814313" t="d" c="43" ts="2410301806" ts-tts="24-10-30 18:06:31.035"/>
    </ar>
    <dp ct="2410302026">
        <m id="r8803875" t="q" c="80" ts="2410301441" ts-tts="24-10-30 14:41:29.430"/>
        <m id="r8803877" t="q" c="80" ts="2410301441" ts-tts="24-10-30 14:41:29.430"/>
        <m id="r8811546" t="f" c="0" ts="2410301719" ts-tts="24-10-30 17:19:11.884"/>
        <m id="r8812304" t="f" c="0" ts="2410301730" ts-tts="24-10-30 17:30:18.463"/>
        <m id="r8814313" t="d" c="43" ts="2410301806" ts-tts="24-10-30 18:06:31.035"/>
        <m id="r8819940" t="f" c="0" ts="2410301952" ts-tts="24-10-30 19:52:13.759"/>
        <m id="r8819942" t="f" c="0" ts="2410301952" ts-tts="24-10-30 19:52:13.759"/>
        <m id="r8819943" t="f" c="0" ts="2410301952" ts-tts="24-10-30 19:52:13.759"/>
        <m id="r8819948" t="f" c="0" ts="2410301952" ts-tts="24-10-30 19:52:13.759"/>
        <m id="r8819953" t="f" c="0" ts="2410301952" ts-tts="24-10-30 19:52:29.552"/>
        <m id="r8819963" t="f" c="0" ts="2410301952" ts-tts="24-10-30 19:52:29.552"/>
    </dp>
</s>


<s id="8428028954903351107-2410301636-11" eva="8000105">
    <m id="r2306090" t="h" from="2410301642" to="2410302000" cat="Störung" ts="2410301643" ts-tts="24-10-30 19:16:12.377" pr="1"/>
    <ar ct="2410302035">
        <m id="r8809514" t="d" c="51" ts="2410301641" ts-tts="24-10-30 16:41:14.639"/>
    </ar>
    <dp ct="2410302041">
        <m id="r8807912" t="f" c="0" ts="2410301607" ts-tts="24-10-30 16:07:22.477"/>
        <m id="r8809514" t="d" c="51" ts="2410301641" ts-tts="24-10-30 16:41:14.639"/>
    </dp>
</s>


<s id="7226217952501399063-2410302347-1" eva="8000105">
    <dp ct="2410302347" l="RB12"/>
</s>


<s id="-8454454517290803659-2410301829-15" eva="8000105">
    <m id="r2304423" t="h" from="2410280806" to="2411102359" cat="Information" ts="2410280813" ts-tts="24-10-29 23:16:14.147" pr="2"/>
    <ar cpth="Bremen Hbf|Osnabrück Hbf|Münster(Westf)Hbf|Dortmund Hbf|Bochum Hbf|Essen Hbf|Duisburg Hbf|Düsseldorf Hbf|Köln Hbf|Frankfurt(M) Flughafen Fernbf" ct="2410310135">
        <m id="r8808225" t="f" c="0" ts="2410301612" ts-tts="24-10-30 16:12:28.569"/>
        <m id="r8808625" t="f" c="0" ts="2410301622" ts-tts="24-10-30 16:22:42.572"/>
    </ar>
</s>


<s id="-7196265674974663958-2410302302-10" eva="8000105">
    <ar ct="2410302340" l="RB12"/>
</s>


<s id="-4384291237910028934-2410301726-27" eva="8000105">
    <ar ct="2410302036" l="54"/>
</s>


<s id="3100468674431110394-2410302008-1" eva="8000105">
    <dp ct="2410302009" l="3">
        <m id="r8817830" t="f" c="0" ts="2410301905" ts-tts="24-10-30 19:06:02.184"/>
        <m id="r8819950" t="f" c="0" ts="2410301952" ts-tts="24-10-30 19:52:29.552"/>
        <m id="r8819952" t="f" c="0" ts="2410301952" ts-tts="24-10-30 19:52:29.552"/>
    </dp>
</s>

</timetable>
