<timetable station="Frankfurt(Main)Hbf" eva="8000105">

<s id="6070111901823858771-2411011529-14" eva="8000105">
    <m id="r2307396" t="h" from="2411011224" to="2411012359" cat="Störung" ts="2411011239" ts-tts="24-11-01 15:16:10.598" pr="1"/>
    <m id="r2307465" t="h" from="2411011529" to="2411012103" cat="Information" ts="2411011526" ts-tts="24-11-01 15:26:32.814" pr="2"/>
    <m id="r2304423" t="h" from="2410280806" to="2411102359" cat="Information" ts="2410280813" ts-tts="24-10-31 23:16:12.208" pr="2"/>
    <ar cpth="Hamburg-Altona|Hamburg Dammtor|Hamburg Hbf|Hamburg-Harburg|Bremen Hbf|Osnabrück Hbf|Münster(Westf)Hbf|Dortmund Hbf|Hagen Hbf|Wuppertal Hbf|Düsseldorf Hbf|Köln Hbf|Frankfurt(M) Flughafen Fernbf" ct="2411012124">
        <m id="r8895513" t="q" c="80" ts="2411011459" ts-tts="24-11-01 14:59:21.208"/>
        <m id="r8895515" t="q" c="80" ts="2411011459" ts-tts="24-11-01 14:59:21.208"/>
        <m id="r8901302" t="d" c="17" ts="2411011724" ts-tts="24-11-01 17:24:09.086"/>
        <m id="r8901318" t="q" c="80" ts="2411011724" ts-tts="24-11-01 17:24:40.180"/>
        <m id="r8901320" t="q" c="80" ts="2411011724" ts-tts="24-11-01 17:24:40.180"/>
        <m id="r8901324" t="d" c="17" ts="2411011724" ts-tts="24-11-01 17:24:40.180"/>
    </ar>
</s>


<s id="486550677600814042-2411011907-13" eva="8000105">
    <ar cp="9" ct="2411012036" l="50">
        <m id="r8888527" t="f" c="0" ts="2411011152" ts-tts="24-11-01 11:52:09.611"/>
        <m id="r8888528" t="f" c="1000" ts="2411011152" ts-tts="24-11-01 11:52:09.611"/>
        <m id="r8888529" t="q" c="74" ts="2411011152" ts-tts="24-11-01 11:52:09.611"/>
    </ar>
</s>


<s id="2312296716933966404-2411011554-13" eva="8000105">
    <ar ct="2411012245">
        <m id="r8904121" t="d" c="43" ts="2411011841" ts-tts="24-11-01 18:41:40.744"/>
    </ar>
    <dp ct="2411012251">
        <m id="r8904121" t="d" c="43" ts="2411011841" ts-tts="24-11-01 18:41:40.744"/>
    </dp>
</s>


<s id="170093097875396020-2411011916-6" eva="8000105">
    <m id="r2307082" t="h" from="2411010200" to="2411040700" cat="Störung" ts="2411010234" ts-tts="24-11-01 02:34:14.388" pr="1"/>
    <m id="r2307533" t="h" from="2411011930" to="2411012359" cat="Störung" ts="2411012031" ts-tts="24-11-01 20:31:31.588" pr="1"/>
    <ar ct="2411012312">
        <m id="r8901317" t="f" c="0" ts="2411011724" ts-tts="24-11-01 17:24:24.673"/>
        <m id="r8904268" t="q" c="80" ts="2411011846" ts-tts="24-11-01 18:46:20.592"/>
        <m id="r8904270" t="q" c="80" ts="2411011846" ts-tts="24-11-01 18:46:20.592"/>
        <m id="r8905286" t="d" c="47" ts="2411011907" ts-tts="24-11-01 19:07:20.430"/>
    </ar>
    <dp ct="2411012318">
        <m id="r8901317" t="f" c="0" ts="2411011724" ts-tts="24-11-01 17:24:24.673"/>
        <m id="r8904268" t="q" c="80" ts="2411011846" ts-tts="24-11-01 18:46:20.592"/>
        <m id="r8904270" t="q" c="80" ts="2411011846" ts-tts="24-11-01 18:46:20.592"/>
        <m id="r8905286" t="d" c="47" ts="2411011907" ts-tts="24-11-01 19:07:20.430"/>
    </dp>
</s>


<s id="6084542420969462186-2411011726-8" eva="8000105">
    <m id="r2307533" t="h" from="2411011930" to="2411012359" cat="Störung" ts="2411012031" ts-tts="24-11-01 20:31:31.588" pr="1"/>
    <ar ct="2411012156">
        <m id="r8895711" t="f" c="0" ts="2411011504" ts-tts="24-11-01 15:04:16.394"/>
        <m id="r8900388" t="q" c="80" ts="2411011702" ts-tts="24-11-01 17:02:37.423"/>
        <m id="r8900390" t="q" c="80" ts="2411011702" ts-tts="24-11-01 17:02:37.423"/>
        <m id="r8900392" t="q" c="80" ts="2411011702" ts-tts="24-11-01 17:02:37.423"/>
        <m id="r8902080" t="d" c="43" ts="2411011745" ts-tts="24-11-01 17:45:55.754"/>
        <m id="r8902252" t="d" c="55" ts="2411011750" ts-tts="24-11-01 17:50:51.703"/>
        <m id="r8906746" t="f" c="0" ts="2411011949" ts-tts="24-11-01 19:49:50.169"/>
        <m id="r8906985" t="f" c="0" ts="2411011959" ts-tts="24-11-01 19:59:08.810"/>
    </ar>
    <dp ct="2411012202">
        <m id="r8895711" t="f" c="0" ts="2411011504" ts-tts="24-11-01 15:04:16.394"/>
        <m id="r8900388" t="q" c="80" ts="2411011702" ts-tts="24-11-01 17:02:37.423"/>
        <m id="r8900390" t="q" c="80" ts="2411011702" ts-tts="24-11-01 17:02:37.423"/>
        <m id="r8900392" t="q" c="80" ts="2411011702" ts-tts="24-11-01 17:02:37.423"/>
        <m id="r8902080" t="d" c="43" ts="2411011745" ts-tts="24-11-01 17:45:55.754"/>
        <m id="r8902252" t="d" c="55" ts="2411011750" ts-tts="24-11-01 17:50:51.703"/>
        <m id="r8906746" t="f" c="0" ts="2411011949" ts-tts="24-11-01 19:49:50.169"/>
        <m id="r8906985" t="f" c="0" ts="2411011959" ts-tts="24-11-01 19:59:08.810"/>
    </dp>
</s>


<s id="5240138407908014065-2411012032-1" eva="8000105">
    <m id="r2220185" t="h" from="2409062032" to="2412010548" cat="Bauarbeiten" ts="2408230832" ts-tts="24-10-31 23:16:11.815" pr="1" del="1"/>
    <dp cp="1" ct="2411012033"/>
</s>


<s id="5089820149948252230-2411011646-8" eva="8000105">
    <ar ct="2411012051">
        <m id="r8905809" t="d" c="43" ts="2411011922" ts-tts="24-11-01 19:22:38.860"/>
    </ar>
</s>


<s id="3283072955374074575-2411011823-12" eva="8000105">
    <ar ct="2411012054" l="30">
        <m id="r8904630" t="d" c="43" ts="2411011855" ts-tts="24-11-01 18:55:24.881"/>
    </ar>
</s>


<s id="8514711408085887329-2411011628-14" eva="8000105">
    <m id="r2307082" t="h" from="2411010200" to="2411040700" cat="Störung" ts="2411010234" ts-tts="24-11-01 02:34:14.388" pr="1"/>
    <m id="r2276258" t="h" from="2409111443" to="2411112359" cat="Information" ts="2409120821" ts-tts="24-10-31 23:16:11.842" pr="2"/>
    <ar cpth="Hamburg-Harburg|Lüneburg|Uelzen|Celle|Hannover Hbf|Göttingen|Kassel-Wilhelmshöhe|Wabern(Bz Kassel)|Treysa|Marburg(Lahn)|Gießen|Friedberg(Hess)" ct="2411012127">
        <m id="r8869518" t="d" c="31" ts="2410312047" ts-tts="24-10-31 20:47:58.963"/>
        <m id="r8869549" t="d" c="31" ts="2410312048" ts-tts="24-10-31 20:48:14.497"/>
        <m id="r8899556" t="d" c="48" ts="2411011641" ts-tts="24-11-01 16:42:09.827"/>
    </ar>
</s>


<s id="-8147699513644188353-2411011817-6" eva="8000105">
    <m id="r2307082" t="h" from="2411010200" to="2411040700" cat="Störung" ts="2411010234" ts-tts="24-11-01 02:34:14.388" pr="1"/>
    <m id="r2307533" t="h" from="2411011930" to="2411012359" cat="Störung" ts="2411012031" ts-tts="24-11-01 20:31:31.588" pr="1"/>
    <ar ct="2411012214">
        <m id="r8902137" t="q" c="80" ts="2411011747" ts-tts="24-11-01 17:47:29.230"/>
        <m id="r8902139" t="q" c="80" ts="2411011747" ts-tts="24-11-01 17:47:29.230"/>
        <m id="r8906438" t="d" c="34" ts="2411011940" ts-tts="24-11-01 19:40:46.890"/>
    </ar>
    <dp ct="2411012221">
        <m id="r8902137" t="q" c="80" ts="2411011747" ts-tts="24-11-01 17:47:29.230"/>
        <m id="r8902139" t="q" c="80" ts="2411011747" ts-tts="24-11-01 17:47:29.230"/>
        <m id="r8906438" t="d" c="34" ts="2411011940" ts-tts="24-11-01 19:40:46.890"/>
    </dp>
</s>


<s id="-3796127802528080561-2411012026-1" eva="8000105">
    <dp ct="2411012032" l="50"/>
</s>

</timetable>
