<timetable station="Frankfurt(Main)Hbf" eva="8000105">

<s id="8667970876619031895-2411010931-23" eva="8000105">
    <ar ct="2411011132" l="RB40"/>
</s>


<s id="-7076418821650022285-2411011026-1" eva="8000105">
    <dp ct="2411011026" l="50">
        <m id="r8879153" t="f" c="0" ts="2411010624" ts-tts="24-11-01 06:24:57.637"/>
        <m id="r8879154" t="f" c="1000" ts="2411010624" ts-tts="24-11-01 06:24:57.638"/>
        <m id="r8879155" t="q" c="92" ts="2411010624" ts-tts="24-11-01 06:24:57.638"/>
        <m id="r8879156" t="f" c="0" ts="2411010625" ts-tts="24-11-01 06:25:13.022"/>
        <m id="r8879157" t="f" c="1000" ts="2411010625" ts-tts="24-11-01 06:25:13.022"/>
        <m id="r8879158" t="q" c="93" ts="2411010625" ts-tts="24-11-01 06:25:13.022"/>
    </dp>
</s>


<s id="-586348946242638825-2411010612-8" eva="8000105">
    <m id="r2307062" t="h" from="2410312200" to="2411011600" cat="Störung" ts="2410312313" ts-tts="24-11-01 08:16:05.078" pr="1"/>
    <m id="r2307172" t="h" from="2411010519" to="2411011600" cat="Information" ts="2411010607" ts-tts="24-11-01 08:16:05.082" pr="1"/>
    <m id="r2307082" t="h" from="2411010200" to="2411040700" cat="Störung" ts="2411010234" ts-tts="24-11-01 02:34:14.388" pr="1"/>
    <m id="r2276258" t="h" from="2409111443" to="2411112359" cat="Information" ts="2409120821" ts-tts="24-10-31 23:16:11.842" pr="2"/>
    <ar cpth="Hamburg Dammtor|Hamburg Hbf|Hamburg-Harburg|Lüneburg|Hannover Hbf|Göttingen|Kassel-Wilhelmshöhe" cp="7" ct="2411010959">
        <m id="r8877816" t="d" c="42" ts="2411010444" ts-tts="24-11-01 04:44:17.102"/>
        <m id="r8878530" t="q" c="80" ts="2411010542" ts-tts="24-11-01 05:42:31.409"/>
        <m id="r8878532" t="q" c="84" ts="2411010542" ts-tts="24-11-01 05:42:31.409"/>
        <m id="r8878534" t="q" c="84" ts="2411010542" ts-tts="24-11-01 05:42:31.409"/>
        <m id="r8883370" t="d" c="35" ts="2411010914" ts-tts="24-11-01 09:14:14.991"/>
        <m id="r8883403" t="f" c="0" ts="2411010915" ts-tts="24-11-01 09:15:17.642"/>
        <m id="r8883503" t="f" c="0" ts="2411010919" ts-tts="24-11-01 09:19:40.672"/>
        <m id="r8884420" t="f" c="0" ts="2411010944" ts-tts="24-11-01 09:44:40.021"/>
        <m id="r8884421" t="f" c="0" ts="2411010944" ts-tts="24-11-01 09:44:40.021"/>
        <m id="r8884445" t="f" c="0" ts="2411010945" ts-tts="24-11-01 09:45:26.603"/>
    </ar>
    <dp cpth="Mainz Hbf|Mannheim Hbf|Karlsruhe Hbf|Baden-Baden|Offenburg|Freiburg(Breisgau) Hbf|Basel Bad Bf|Basel SBB" cp="7" ct="2411011006">
        <m id="r8877816" t="d" c="42" ts="2411010444" ts-tts="24-11-01 04:44:17.102"/>
        <m id="r8878530" t="q" c="80" ts="2411010542" ts-tts="24-11-01 05:42:31.409"/>
        <m id="r8878532" t="q" c="84" ts="2411010542" ts-tts="24-11-01 05:42:31.409"/>
        <m id="r8878534" t="q" c="84" ts="2411010542" ts-tts="24-11-01 05:42:31.409"/>
        <m id="r8883370" t="d" c="35" ts="2411010914" ts-tts="24-11-01 09:14:14.991"/>
        <m id="r8883403" t="f" c="0" ts="2411010915" ts-tts="24-11-01 09:15:17.642"/>
        <m id="r8883503" t="f" c="0" ts="2411010919" ts-tts="24-11-01 09:19:40.672"/>
        <m id="r8884420" t="f" c="0" ts="2411010944" ts-tts="24-11-01 09:44:40.021"/>
        <m id="r8884421" t="f" c="0" ts="2411010944" ts-tts="24-11-01 09:44:40.021"/>
        <m id="r8884445" t="f" c="0" ts="2411010945" ts-tts="24-11-01 09:45:26.603"/>
    </dp>
</s>


<s id="8586438261096316872-2411010907-15" eva="8000105">
    <ar ct="2411011026" l="68">
        <m id="r8883357" t="d" c="45" ts="2411010913" ts-tts="24-11-01 09:13:59.621"/>
        <m id="r8884590" t="d" c="45" ts="2411010946" ts-tts="24-11-01 09:46:13.050"/>
    </ar>
</s>


<s id="4673768552777499691-2411010833-14" eva="8000105">
    <ar cp="12" ct="2411010958" l="60">
        <m id="r8883228" t="d" c="43" ts="2411010907" ts-tts="24-11-01 09:07:33.389"/>
        <m id="r8883335" t="d" c="45" ts="2411010912" ts-tts="24-11-01 09:12:27.068"/>
        <m id="r8884115" t="d" c="45" ts="2411010937" ts-tts="24-11-01 09:37:27.313"/>
    </ar>
</s>


<s id="-6382331557337532208-2411011025-8" eva="8000105">
    <ar ct="2411011338">
        <m id="r8884811" t="q" c="80" ts="2411010955" ts-tts="24-11-01 09:55:29.608"/>
    </ar>
</s>


<s id="6857733995447485164-2411011115-6" eva="8000105">
    <m id="r2307062" t="h" from="2410312200" to="2411011600" cat="Störung" ts="2410312313" ts-tts="24-11-01 08:16:05.078" pr="1"/>
    <m id="r2307172" t="h" from="2411010519" to="2411011600" cat="Information" ts="2411010607" ts-tts="24-11-01 08:16:05.082" pr="1"/>
    <m id="r2307082" t="h" from="2411010200" to="2411040700" cat="Störung" ts="2411010234" ts-tts="24-11-01 02:34:14.388" pr="1"/>
    <ar cpth="Hamburg Dammtor|Hamburg Hbf|Hannover Hbf|Göttingen|Kassel-Wilhelmshöhe">
        <m id="r8882920" t="d" c="35" ts="2411010855" ts-tts="24-11-01 08:55:27.471"/>
        <m id="r8882967" t="f" c="0" ts="2411010857" ts-tts="24-11-01 08:57:15.389"/>
        <m id="r8884819" t="f" c="0" ts="2411010955" ts-tts="24-11-01 09:55:45.049"/>
    </ar>
    <dp cpth="Mainz Hbf|Mannheim Hbf|Stuttgart Hbf|Ulm Hbf|Augsburg Hbf|München-Pasing|München Hbf" cs="p" clt="2411010855">
        <m id="r8882920" t="d" c="35" ts="2411010855" ts-tts="24-11-01 08:55:27.471"/>
        <m id="r8882967" t="f" c="0" ts="2411010857" ts-tts="24-11-01 08:57:15.389"/>
        <m id="r8884819" t="f" c="0" ts="2411010955" ts-tts="24-11-01 09:55:45.049"/>
    </dp>
</s>


<s id="-7306060287928860392-2411010915-6" eva="8000105">
    <m id="r2307062" t="h" from="2410312200" to="2411011600" cat="Störung" ts="2410312313" ts-tts="24-11-01 08:16:05.078" pr="1"/>
    <m id="r2307172" t="h" from="2411010519" to="2411011600" cat="Information" ts="2411010607" ts-tts="24-11-01 08:16:05.082" pr="1"/>
    <m id="r2307082" t="h" from="2411010200" to="2411040700" cat="Störung" ts="2411010234" ts-tts="24-11-01 02:34:14.388" pr="1"/>
    <m id="r2307152" t="h" from="2411010100" to="2411011600" cat="Störung" ts="2411010510" ts-tts="24-11-01 08:16:05.080" pr="2"/>
    <ar cpth="Hamburg Dammtor|Hamburg Hbf|Hannover Hbf|Göttingen|Kassel-Wilhelmshöhe" ct="2411011300">
        <m id="r8878861" t="f" c="0" ts="2411010606" ts-tts="24-11-01 06:06:56.312"/>
        <m id="r8882520" t="q" c="80" ts="2411010845" ts-tts="24-11-01 08:45:09.646"/>
        <m id="r8882524" t="q" c="80" ts="2411010845" ts-tts="24-11-01 08:45:09.646"/>
        <m id="r8882535" t="q" c="80" ts="2411010845" ts-tts="24-11-01 08:45:25.111"/>
        <m id="r8882537" t="q" c="80" ts="2411010845" ts-tts="24-11-01 08:45:25.111"/>
        <m id="r8882982" t="d" c="35" ts="2411010857" ts-tts="24-11-01 08:57:30.899"/>
        <m id="r8884813" t="f" c="0" ts="2411010955" ts-tts="24-11-01 09:55:29.608"/>
        <m id="r8884820" t="q" c="84" ts="2411010955" ts-tts="24-11-01 09:55:45.048"/>
        <m id="r8884822" t="q" c="84" ts="2411010955" ts-tts="24-11-01 09:55:45.048"/>
    </ar>
    <dp cpth="Mainz Hbf|Mannheim Hbf|Stuttgart Hbf|Ulm Hbf|Augsburg Hbf|München-Pasing|München Hbf" ct="2411011307" cs="p" clt="2411010857">
        <m id="r8878861" t="f" c="0" ts="2411010606" ts-tts="24-11-01 06:06:56.312"/>
        <m id="r8882520" t="q" c="80" ts="2411010845" ts-tts="24-11-01 08:45:09.646"/>
        <m id="r8882524" t="q" c="80" ts="2411010845" ts-tts="24-11-01 08:45:09.647"/>
        <m id="r8882535" t="q" c="80" ts="2411010845" ts-tts="24-11-01 08:45:25.111"/>
        <m id="r8882537" t="q" c="80" ts="2411010845" ts-tts="24-11-01 08:45:25.111"/>
        <m id="r8882982" t="d" c="35" ts="2411010857" ts-tts="24-11-01 08:57:30.899"/>
        <m id="r8884813" t="f" c="0" ts="2411010955" ts-tts="24-11-01 09:55:29.608"/>
        <m id="r8884820" t="q" c="84" ts="2411010955" ts-tts="24-11-01 09:55:45.048"/>
        <m id="r8884822" t="q" c="84" ts="2411010955" ts-tts="24-11-01 09:55:45.048"/>
    </dp>
</s>


<s id="8774939972882156309-2411011025-1" eva="8000105">
    <dp ct="2411011025" l="RB82"/>
</s>


<s id="-1361694642872222341-2411010542-4" eva="8000105">
    <ar cp="11" ct="2411010956"/>
</s>


<s id="6512907201443103756-2411010926-1" eva="8000105">
    <dp cp="12" ct="2411010954">
        <m id="r8882946" t="q" c="80" ts="2411010856" ts-tts="24-11-01 08:56:29.068"/>
        <m id="r8883094" t="d" c="47" ts="2411010901" ts-tts="24-11-01 09:01:22.501"/>
    </dp>
</s>


<s id="2939215180105942175-2411011006-1" eva="8000105">
    <dp cp="12" ct="2411011006" l="60"/>
</s>


<s id="-4617228405729794669-2411010829-9" eva="8000105">
    <ar ct="2411011238">
        <m id="r8882162" t="d" c="61" ts="2411010832" ts-tts="24-11-01 08:32:47.631"/>
    </ar>
</s>


<s id="-1099707498340369858-2411011046-8" eva="8000105">
    <m id="r2307062" t="h" from="2410312200" to="2411011600" cat="Störung" ts="2410312313" ts-tts="24-11-01 08:16:05.078" pr="1"/>
    <m id="r2307172" t="h" from="2411010519" to="2411011600" cat="Information" ts="2411010607" ts-tts="24-11-01 08:16:05.082" pr="1"/>
    <m id="r2307082" t="h" from="2411010200" to="2411040700" cat="Störung" ts="2411010234" ts-tts="24-11-01 02:34:14.387" pr="1"/>
    <m id="r2307152" t="h" from="2411010100" to="2411011600" cat="Störung" ts="2411010510" ts-tts="24-11-01 08:16:05.080" pr="2"/>
    <ar cpth="München Hbf|München-Pasing|Augsburg Hbf|Ulm Hbf|Stuttgart Hbf|Mannheim Hbf|Mainz Hbf" cs="p" clt="2411010854">
        <m id="r8882899" t="d" c="35" ts="2411010854" ts-tts="24-11-01 08:54:41.121"/>
        <m id="r8884805" t="f" c="0" ts="2411010954" ts-tts="24-11-01 09:54:58.724"/>
    </ar>
    <dp cpth="Kassel-Wilhelmshöhe|Göttingen|Hannover Hbf|Hamburg Hbf" cs="p" clt="2411010854">
        <m id="r8882899" t="d" c="35" ts="2411010854" ts-tts="24-11-01 08:54:41.121"/>
        <m id="r8884805" t="f" c="0" ts="2411010954" ts-tts="24-11-01 09:54:58.724"/>
    </dp>
</s>


<m id="r125561" t="r" from="2411010904" to="2411010952" ts="2411010952" ts-tts="24-11-01 09:53:10.500"/>

</timetable>
