<timetable station="Frankfurt(Main)Hbf" eva="8000105">

<s id="1485629325294874690-2411032006-1" eva="8000105">
    <dp ct="2411032006" l="60">
        <m id="r8964107" t="q" c="82" ts="2411031613" ts-tts="24-11-03 16:13:07.046"/>
    </dp>
</s>


<s id="-8005609635293134624-2411031716-6" eva="8000105">
    <m id="r2308834" t="h" from="2411031724" to="2411072359" cat="Information" ts="2411031725" ts-tts="24-11-03 17:25:54.316" pr="3"/>
    <ar ppth="Hamburg Dammtor|Hamburg Hbf|Hannover Hbf|Göttingen|Kassel-Wilhelmshöhe" pp="6" ct="2411032151" pt="2411032100">
        <m id="r8965418" t="q" c="80" ts="2411031646" ts-tts="24-11-03 16:46:24.633"/>
        <m id="r8965420" t="q" c="84" ts="2411031646" ts-tts="24-11-03 16:46:24.633"/>
        <m id="r8965422" t="q" c="84" ts="2411031646" ts-tts="24-11-03 16:46:24.633"/>
        <m id="r8967558" t="q" c="85" ts="2411031736" ts-tts="24-11-03 17:36:45.642"/>
        <m id="r8968333" t="d" c="5" ts="2411031758" ts-tts="24-11-03 17:58:26.286"/>
        <m id="r8968824" t="f" c="0" ts="2411031811" ts-tts="24-11-03 18:11:37.531"/>
        <m id="r8969362" t="f" c="0" ts="2411031822" ts-tts="24-11-03 18:23:00.780"/>
        <m id="r8970512" t="f" c="0" ts="2411031852" ts-tts="24-11-03 18:52:44.517"/>
    </ar>
    <dp ppth="Mainz Hbf|Mannheim Hbf|Stuttgart Hbf|Ulm Hbf|Günzburg|Augsburg Hbf|München-Pasing|München Hbf" pp="6" ct="2411032157" pt="2411032105">
        <m id="r8965418" t="q" c="80" ts="2411031646" ts-tts="24-11-03 16:46:24.633"/>
        <m id="r8965420" t="q" c="84" ts="2411031646" ts-tts="24-11-03 16:46:24.633"/>
        <m id="r8965422" t="q" c="84" ts="2411031646" ts-tts="24-11-03 16:46:24.633"/>
        <m id="r8967558" t="q" c="85" ts="2411031736" ts-tts="24-11-03 17:36:45.642"/>
        <m id="r8968333" t="d" c="5" ts="2411031758" ts-tts="24-11-03 17:58:26.286"/>
        <m id="r8968824" t="f" c="0" ts="2411031811" ts-tts="24-11-03 18:11:37.531"/>
        <m id="r8969362" t="f" c="0" ts="2411031822" ts-tts="24-11-03 18:23:00.780"/>
        <m id="r8970512" t="f" c="0" ts="2411031852" ts-tts="24-11-03 18:52:44.517"/>
    </dp>
    <tl f="F" t="p" o="80" c="ICE" n="695"/>
</s>


<s id="-7573651573329216408-2411031500-15" eva="8000105">
    <m id="r2185587" t="h" from="2407160000" to="2412142359" cat="Information" ts="2408230832" ts-tts="24-11-02 23:16:09.633" pr="2" del="1"/>
    <ar ct="2411032008">
        <m id="r8960012" t="q" c="80" ts="2411031430" ts-tts="24-11-03 14:30:30.819"/>
        <m id="r8960014" t="q" c="80" ts="2411031430" ts-tts="24-11-03 14:30:30.819"/>
        <m id="r8960016" t="q" c="80" ts="2411031430" ts-tts="24-11-03 14:30:30.819"/>
        <m id="r8960018" t="q" c="80" ts="2411031430" ts-tts="24-11-03 14:30:30.819"/>
        <m id="r8970305" t="f" c="0" ts="2411031848" ts-tts="24-11-03 18:48:51.888"/>
    </ar>
    <dp ct="2411032016">
        <m id="r8960012" t="q" c="80" ts="2411031430" ts-tts="24-11-03 14:30:30.819"/>
        <m id="r8960014" t="q" c="80" ts="2411031430" ts-tts="24-11-03 14:30:30.819"/>
        <m id="r8960016" t="q" c="80" ts="2411031430" ts-tts="24-11-03 14:30:30.819"/>
        <m id="r8960018" t="q" c="80" ts="2411031430" ts-tts="24-11-03 14:30:30.819"/>
        <m id="r8970305" t="f" c="0" ts="2411031848" ts-tts="24-11-03 18:48:51.888"/>
    </dp>
</s>


<s id="-8312398823745694210-2411031511-8" eva="8000105">
    <m id="r2279816" t="h" from="2410311511" to="2411032359" cat="Bauarbeiten" ts="2410302302" ts-tts="24-11-02 23:16:09.668" pr="1"/>
    <m id="r2308834" t="h" from="2411031724" to="2411072359" cat="Information" ts="2411031725" ts-tts="24-11-03 17:25:54.317" pr="3"/>
    <ar ct="2411032008">
        <m id="r8967947" t="d" c="54" ts="2411031746" ts-tts="24-11-03 17:46:34.386"/>
    </ar>
    <dp ct="2411032014">
        <m id="r8967947" t="d" c="54" ts="2411031746" ts-tts="24-11-03 17:46:34.386"/>
    </dp>
</s>


<s id="3639185015027004194-2411031610-10" eva="8000105">
    <ar ct="2411032041">
        <m id="r8970378" t="d" c="31" ts="2411031850" ts-tts="24-11-03 18:50:40.576"/>
    </ar>
</s>


<s id="-6530686665708997936-2411031916-13" eva="8000105">
    <ar ct="2411032018" l="51">
        <m id="r8971835" t="d" c="43" ts="2411031923" ts-tts="24-11-03 19:23:15.353"/>
        <m id="r8972652" t="d" c="43" ts="2411031939" ts-tts="24-11-03 19:39:17.123"/>
    </ar>
</s>


<s id="4511802780835934709-2411031709-5" eva="8000105">
    <m id="r2285185" t="h" from="2410010000" to="2411152359" cat="Information" ts="2409302303" ts-tts="24-11-02 23:16:09.675" pr="2"/>
    <m id="r2289117" t="h" from="2410100000" to="2411042312" cat="Information" ts="2410092303" ts-tts="24-11-02 23:16:09.809" pr="2"/>
    <ar ct="2411032137">
        <m id="r8972191" t="d" c="43" ts="2411031932" ts-tts="24-11-03 19:32:18.429"/>
    </ar>
</s>


<s id="-6524998557445987060-2411031847-5" eva="8000105">
    <ar ct="2411032222">
        <m id="r8964660" t="f" c="0" ts="2411031628" ts-tts="24-11-03 16:28:20.889"/>
        <m id="r8964680" t="d" c="48" ts="2411031628" ts-tts="24-11-03 16:28:51.822"/>
        <m id="r8966556" t="f" c="0" ts="2411031713" ts-tts="24-11-03 17:14:01.447"/>
        <m id="r8968449" t="f" c="0" ts="2411031802" ts-tts="24-11-03 18:02:34.164"/>
        <m id="r8969039" t="q" c="80" ts="2411031817" ts-tts="24-11-03 18:17:18.754"/>
        <m id="r8969042" t="q" c="80" ts="2411031817" ts-tts="24-11-03 18:17:18.754"/>
        <m id="r8969454" t="f" c="0" ts="2411031825" ts-tts="24-11-03 18:26:06.817"/>
    </ar>
    <dp ct="2411032229">
        <m id="r8964660" t="f" c="0" ts="2411031628" ts-tts="24-11-03 16:28:20.889"/>
        <m id="r8964680" t="d" c="48" ts="2411031628" ts-tts="24-11-03 16:28:51.822"/>
        <m id="r8966556" t="f" c="0" ts="2411031713" ts-tts="24-11-03 17:14:01.447"/>
        <m id="r8968449" t="f" c="0" ts="2411031802" ts-tts="24-11-03 18:02:34.164"/>
        <m id="r8969039" t="q" c="80" ts="2411031817" ts-tts="24-11-03 18:17:18.754"/>
        <m id="r8969042" t="q" c="80" ts="2411031817" ts-tts="24-11-03 18:17:18.754"/>
        <m id="r8969454" t="f" c="0" ts="2411031825" ts-tts="24-11-03 18:26:06.817"/>
    </dp>
</s>

</timetable>
